Animals/__init__.py
Animals/livestocks/__init__.py
Animals/livestocks/cow.py
Animals/livestocks/livestock.py
Animals/pet_animals/__init__.py
Animals/pet_animals/cat.py
Animals/pet_animals/pet.py
Animals/userDefineException/__init__.py
Animals/userDefineException/myException1.py
Animals/userDefineException2/__init__.py
Animals/userDefineException2/myException2.py
DATA533LAB4_Animals/__init__.py
DATA533LAB4_Animals/livestocks/__init__.py
DATA533LAB4_Animals/livestocks/cow.py
DATA533LAB4_Animals/livestocks/livestock.py
DATA533LAB4_Animals/pet_animals/__init__.py
DATA533LAB4_Animals/pet_animals/cat.py
DATA533LAB4_Animals/pet_animals/pet.py
DATA533LAB4_Animals/userDefineException/__init__.py
DATA533LAB4_Animals/userDefineException/myException1.py
DATA533LAB4_Animals/userDefineException2/__init__.py
DATA533LAB4_Animals/userDefineException2/myException2.py
DATA533LAB4_Animals-0.1.dist-info/METADATA
DATA533LAB4_Animals-0.1.dist-info/WHEEL
DATA533LAB4_Animals-0.1.dist-info/license.md
DATA533LAB4_Animals-0.1.dist-info/top_level.txt
DATA533LAB4_Animals-0.1.dist-info/RECORD
