Metadata-Version: 2.1
Name: DATA533LAB4-Animals
Version: 0.1
Summary: DATA533_lab4
Home-page: https://github.com/Astarter/DATA533_Lab4
Author: Bohan Gao and Vicens Paneque
Author-email: gbh958810784@gmail.com
License: MIT
Platform: UNKNOWN
